hellomcp/__init__.py
hellomcp/__main__.py
hellomcp/main.py
hellomcp-0.1.5.dist-info/METADATA
hellomcp-0.1.5.dist-info/WHEEL
hellomcp-0.1.5.dist-info/entry_points.txt
hellomcp-0.1.5.dist-info/top_level.txt
hellomcp-0.1.5.dist-info/RECORD
