Metadata-Version: 2.4
Name: hellomcp
Version: 0.1.5
Summary: Add your description here
Requires-Python: >=3.11
Requires-Dist: mcp[cli]>=1.6.0
